LICENSE.txt
MANIFEST.in
README.md
requirements.txt
setup.cfg
setup.py
src/neomaril_codex/__init__.py
src/neomaril_codex/__model_states.py
src/neomaril_codex/__utils.py
src/neomaril_codex/base.py
src/neomaril_codex/datasources.py
src/neomaril_codex/exceptions.py
src/neomaril_codex/logging.py
src/neomaril_codex/model.py
src/neomaril_codex/pipeline.py
src/neomaril_codex/preprocessing.py
src/neomaril_codex/training.py
src/neomaril_codex.egg-info/PKG-INFO
src/neomaril_codex.egg-info/SOURCES.txt
src/neomaril_codex.egg-info/dependency_links.txt
src/neomaril_codex.egg-info/not-zip-safe
src/neomaril_codex.egg-info/requires.txt
src/neomaril_codex.egg-info/top_level.txt