Metadata-Version: 2.1
Name: neomaril-codex
Version: 2.1.1
Summary: Python tools for interact with Neomaril
Home-page: https://datarisk-io.github.io/mlops-neomaril-codex/
Download-URL: https://github.com/datarisk-io/mlops-neomaril-codex/archive/refs/tags/v2.1.1.tar.gz
Author: Datarisk
Classifier: Programming Language :: Python :: 3
License-File: LICENSE.txt
Requires-Dist: requests==2.32.3
Requires-Dist: loguru==0.6.0
Requires-Dist: pyyaml
Requires-Dist: python-dotenv==0.21.0
Requires-Dist: cachetools
Requires-Dist: cloudpickle>=2.0.0
Requires-Dist: pyarrow>=1.0.0
Requires-Dist: pandas>=1.0.0
Requires-Dist: lazy-imports==0.3.1
